MANIFEST.in
README.md
dev-requirements.txt
requirements.txt
setup.py
pipeline/__init__.py
pipeline/urls.py
pipeline/wsgi.py
pycon/__init__.py
pycon/admin.py
pycon/apps.py
pycon/models.py
pycon/tests.py
pycon/urls.py
pycon/utils.py
pycon/views.py
pycon/migrations/__init__.py
pycon/templates/pycon.html
pycon_ng2019.egg-info/PKG-INFO
pycon_ng2019.egg-info/SOURCES.txt
pycon_ng2019.egg-info/dependency_links.txt
pycon_ng2019.egg-info/requires.txt
pycon_ng2019.egg-info/top_level.txt