Metadata-Version: 2.1
Name: pycon-ng2019
Version: 1.0.0
Summary: Welcome to Pycon Nigeria 2019
Home-page: https://github.com/bisoncorps/pipelining-pycon-talk
Author: Domnan Diretnan, Mmadu Manasseh
Author-email: diretnandomnan@gmail.com
License: MIT
Keywords: pycon nigeria
Platform: UNKNOWN
Classifier: Programming Language :: Python :: 3
Classifier: License :: OSI Approved :: MIT License
Classifier: Operating System :: OS Independent
Requires-Python: >=3.6
